git_pluse/__init__.py
git_pluse/analyzer.py
git_pluse/cli.py
git_pluse-1.0.0.dist-info/licenses/LICENSE
test/__init__.py
test/test_cli.py
git_pluse-1.0.0.dist-info/METADATA
git_pluse-1.0.0.dist-info/WHEEL
git_pluse-1.0.0.dist-info/entry_points.txt
git_pluse-1.0.0.dist-info/top_level.txt
git_pluse-1.0.0.dist-info/RECORD
