Metadata-Version: 2.4
Name: git-pluse
Version: 1.0.0
Summary: GitHub commit analyzer - analyze and visualize commit frequency
Home-page: https://github.com/erquren/git-pluse
Author: erquren
Author-email: erquren <contact@erquren.com>
License: MIT
Project-URL: Homepage, https://github.com/erquren/git-pluse
Project-URL: Repository, https://github.com/erquren/git-pluse
Project-URL: Issues, https://github.com/erquren/git-pluse/issues
Keywords: github,git,commit,analysis,visualization
Classifier: Development Status :: 5 - Production/Stable
Classifier: Intended Audience :: Developers
Classifier: Topic :: Software Development :: Version Control
Classifier: License :: OSI Approved :: MIT License
Classifier: Programming Language :: Python :: 3
Classifier: Programming Language :: Python :: 3.7
Classifier: Programming Language :: Python :: 3.8
Classifier: Programming Language :: Python :: 3.9
Classifier: Programming Language :: Python :: 3.10
Classifier: Programming Language :: Python :: 3.11
Classifier: Programming Language :: Python :: 3.12
Classifier: Programming Language :: Python :: 3.13
Requires-Python: >=3.7
License-File: LICENSE
Requires-Dist: requests>=2.25.0
Requires-Dist: matplotlib>=3.3.0
Provides-Extra: dev
Requires-Dist: pytest>=7.0.0; extra == "dev"
Requires-Dist: pytest-cov>=4.0.0; extra == "dev"
Dynamic: author
Dynamic: home-page
Dynamic: license-file
Dynamic: requires-python
